{
  "id":"gyrocopter",
  "matchups":[
    {
      "adv":"2.9969",
      "id":"juggernaut",
      "wr":"46.274"
    },
    {
      "adv":"2.6336",
      "id":"lifestealer",
      "wr":"48.2735"
    },
    {
      "adv":"2.4786",
      "id":"meepo",
      "wr":"44.1254"
    },
    {
      "adv":"2.3639",
      "id":"anti-mage",
      "wr":"45.9858"
    },
    {
      "adv":"1.5097",
      "id":"shadow-demon",
      "wr":"52.8598"
    },
    {
      "adv":"1.3462",
      "id":"phantom-lancer",
      "wr":"49.5518"
    },
    {
      "adv":"1.3451",
      "id":"viper",
      "wr":"50.8801"
    },
    {
      "adv":"1.3226",
      "id":"brewmaster",
      "wr":"49.4136"
    },
    {
      "adv":"1.2875",
      "id":"puck",
      "wr":"52.0675"
    },
    {
      "adv":"1.1989",
      "id":"pudge",
      "wr":"48.5588"
    },
    {
      "adv":"1.1469",
      "id":"huskar",
      "wr":"49.1436"
    },
    {
      "adv":"1.0575",
      "id":"faceless-void",
      "wr":"51.6332"
    },
    {
      "adv":"0.9924",
      "id":"arc-warden",
      "wr":"45.171"
    },
    {
      "adv":"0.9828",
      "id":"bloodseeker",
      "wr":"50.3818"
    },
    {
      "adv":"0.8354",
      "id":"enigma",
      "wr":"51.9715"
    },
    {
      "adv":"0.8251",
      "id":"void-spirit",
      "wr":"51.16"
    },
    {
      "adv":"0.8224",
      "id":"storm-spirit",
      "wr":"53.4138"
    },
    {
      "adv":"0.8027",
      "id":"venomancer",
      "wr":"49.6014"
    },
    {
      "adv":"0.7914",
      "id":"marci",
      "wr":"52.4671"
    },
    {
      "adv":"0.7702",
      "id":"elder-titan",
      "wr":"51.2875"
    },
    {
      "adv":"0.7032",
      "id":"outworld-destroyer",
      "wr":"49.3257"
    },
    {
      "adv":"0.7007",
      "id":"keeper-of-the-light",
      "wr":"53.3787"
    },
    {
      "adv":"0.6957",
      "id":"abaddon",
      "wr":"48.7081"
    },
    {
      "adv":"0.6788",
      "id":"broodmother",
      "wr":"52.0609"
    },
    {
      "adv":"0.6131",
      "id":"spectre",
      "wr":"44.9046"
    },
    {
      "adv":"0.5861",
      "id":"chen",
      "wr":"52.0485"
    },
    {
      "adv":"0.5835",
      "id":"dark-willow",
      "wr":"49.8067"
    },
    {
      "adv":"0.5462",
      "id":"natures-prophet",
      "wr":"54.6283"
    },
    {
      "adv":"0.5146",
      "id":"visage",
      "wr":"47.5021"
    },
    {
      "adv":"0.4879",
      "id":"zeus",
      "wr":"49.3383"
    },
    {
      "adv":"0.4652",
      "id":"ancient-apparition",
      "wr":"48.1476"
    },
    {
      "adv":"0.4594",
      "id":"oracle",
      "wr":"50.3834"
    },
    {
      "adv":"0.4104",
      "id":"tidehunter",
      "wr":"49.379"
    },
    {
      "adv":"0.3774",
      "id":"skywrath-mage",
      "wr":"49.0155"
    },
    {
      "adv":"0.3706",
      "id":"pugna",
      "wr":"53.5993"
    },
    {
      "adv":"0.3468",
      "id":"sniper",
      "wr":"52.021"
    },
    {
      "adv":"0.3113",
      "id":"tinker",
      "wr":"47.732"
    },
    {
      "adv":"0.3091",
      "id":"earth-spirit",
      "wr":"53.2682"
    },
    {
      "adv":"0.3032",
      "id":"ember-spirit",
      "wr":"53.2874"
    },
    {
      "adv":"0.2625",
      "id":"queen-of-pain",
      "wr":"54.7909"
    },
    {
      "adv":"0.2623",
      "id":"lina",
      "wr":"52.4354"
    },
    {
      "adv":"0.2607",
      "id":"tusk",
      "wr":"51.2308"
    },
    {
      "adv":"0.2586",
      "id":"legion-commander",
      "wr":"46.2557"
    },
    {
      "adv":"0.2062",
      "id":"io",
      "wr":"50.7983"
    },
    {
      "adv":"0.1966",
      "id":"naga-siren",
      "wr":"48.391"
    },
    {
      "adv":"0.1745",
      "id":"clockwerk",
      "wr":"50.1188"
    },
    {
      "adv":"0.1442",
      "id":"pangolier",
      "wr":"54.1502"
    },
    {
      "adv":"0.1401",
      "id":"ogre-magi",
      "wr":"51.1544"
    },
    {
      "adv":"0.1343",
      "id":"rubick",
      "wr":"53.629"
    },
    {
      "adv":"0.1215",
      "id":"invoker",
      "wr":"52.7845"
    },
    {
      "adv":"0.1147",
      "id":"magnus",
      "wr":"51.0467"
    },
    {
      "adv":"0.1026",
      "id":"witch-doctor",
      "wr":"48.6914"
    },
    {
      "adv":"0.0991",
      "id":"crystal-maiden",
      "wr":"48.9569"
    },
    {
      "adv":"0.0587",
      "id":"warlock",
      "wr":"48.9964"
    },
    {
      "adv":"0.0549",
      "id":"lich",
      "wr":"48.6377"
    },
    {
      "adv":"0.0499",
      "id":"mirana",
      "wr":"47.4929"
    },
    {
      "adv":"0.0474",
      "id":"snapfire",
      "wr":"52.7218"
    },
    {
      "adv":"0.0442",
      "id":"bane",
      "wr":"53.1637"
    },
    {
      "adv":"0.0355",
      "id":"chaos-knight",
      "wr":"51.2947"
    },
    {
      "adv":"0.0157",
      "id":"underlord",
      "wr":"47.2866"
    },
    {
      "adv":"0.0136",
      "id":"kunkka",
      "wr":"52.7522"
    },
    {
      "adv":"0.013",
      "id":"primal-beast",
      "wr":"52.6336"
    },
    {
      "adv":"-0.005",
      "id":"techies",
      "wr":"49.645"
    },
    {
      "adv":"-0.028",
      "id":"bounty-hunter",
      "wr":"50.5253"
    },
    {
      "adv":"-0.0324",
      "id":"dawnbreaker",
      "wr":"50.3519"
    },
    {
      "adv":"-0.0607",
      "id":"dark-seer",
      "wr":"48.9737"
    },
    {
      "adv":"-0.0643",
      "id":"doom",
      "wr":"53.6398"
    },
    {
      "adv":"-0.0843",
      "id":"leshrac",
      "wr":"51.7444"
    },
    {
      "adv":"-0.0852",
      "id":"sand-king",
      "wr":"49.7473"
    },
    {
      "adv":"-0.1149",
      "id":"centaur-warrunner",
      "wr":"47.7629"
    },
    {
      "adv":"-0.1268",
      "id":"alchemist",
      "wr":"54.466"
    },
    {
      "adv":"-0.1272",
      "id":"phoenix",
      "wr":"51.1924"
    },
    {
      "adv":"-0.1401",
      "id":"dragon-knight",
      "wr":"53.6087"
    },
    {
      "adv":"-0.164",
      "id":"wraith-king",
      "wr":"50.009"
    },
    {
      "adv":"-0.17",
      "id":"luna",
      "wr":"50.3616"
    },
    {
      "adv":"-0.1728",
      "id":"sven",
      "wr":"52.7467"
    },
    {
      "adv":"-0.2015",
      "id":"nyx-assassin",
      "wr":"51.2492"
    },
    {
      "adv":"-0.2031",
      "id":"omniknight",
      "wr":"46.4077"
    },
    {
      "adv":"-0.204",
      "id":"terrorblade",
      "wr":"56.0952"
    },
    {
      "adv":"-0.2093",
      "id":"spirit-breaker",
      "wr":"51.5089"
    },
    {
      "adv":"-0.2339",
      "id":"medusa",
      "wr":"51.8883"
    },
    {
      "adv":"-0.269",
      "id":"mars",
      "wr":"53.5856"
    },
    {
      "adv":"-0.2723",
      "id":"batrider",
      "wr":"56.4493"
    },
    {
      "adv":"-0.2916",
      "id":"treant-protector",
      "wr":"46.4478"
    },
    {
      "adv":"-0.3002",
      "id":"jakiro",
      "wr":"48.6347"
    },
    {
      "adv":"-0.3693",
      "id":"ursa",
      "wr":"50.4336"
    },
    {
      "adv":"-0.3781",
      "id":"enchantress",
      "wr":"54.9441"
    },
    {
      "adv":"-0.3971",
      "id":"morphling",
      "wr":"54.8088"
    },
    {
      "adv":"-0.4042",
      "id":"earthshaker",
      "wr":"50.9932"
    },
    {
      "adv":"-0.4048",
      "id":"razor",
      "wr":"45.5578"
    },
    {
      "adv":"-0.4073",
      "id":"windranger",
      "wr":"51.8678"
    },
    {
      "adv":"-0.4221",
      "id":"shadow-shaman",
      "wr":"49.5984"
    },
    {
      "adv":"-0.4275",
      "id":"riki",
      "wr":"46.0934"
    },
    {
      "adv":"-0.4662",
      "id":"lion",
      "wr":"53.9294"
    },
    {
      "adv":"-0.5114",
      "id":"disruptor",
      "wr":"50.5905"
    },
    {
      "adv":"-0.5283",
      "id":"death-prophet",
      "wr":"50.7961"
    },
    {
      "adv":"-0.534",
      "id":"clinkz",
      "wr":"47.1526"
    },
    {
      "adv":"-0.5529",
      "id":"lone-druid",
      "wr":"48.3444"
    },
    {
      "adv":"-0.5773",
      "id":"timbersaw",
      "wr":"54.1756"
    },
    {
      "adv":"-0.6075",
      "id":"night-stalker",
      "wr":"50.4197"
    },
    {
      "adv":"-0.6426",
      "id":"hoodwink",
      "wr":"51.7519"
    },
    {
      "adv":"-0.6725",
      "id":"beastmaster",
      "wr":"52.8023"
    },
    {
      "adv":"-0.6738",
      "id":"shadow-fiend",
      "wr":"50.3224"
    },
    {
      "adv":"-0.6758",
      "id":"monkey-king",
      "wr":"55.2085"
    },
    {
      "adv":"-0.716",
      "id":"muerta",
      "wr":"56.5279"
    },
    {
      "adv":"-0.7478",
      "id":"slardar",
      "wr":"49.502"
    },
    {
      "adv":"-0.756",
      "id":"vengeful-spirit",
      "wr":"49.9779"
    },
    {
      "adv":"-0.7777",
      "id":"winter-wyvern",
      "wr":"53.0925"
    },
    {
      "adv":"-0.7781",
      "id":"weaver",
      "wr":"52.9934"
    },
    {
      "adv":"-0.7807",
      "id":"tiny",
      "wr":"53.966"
    },
    {
      "adv":"-0.8138",
      "id":"grimstroke",
      "wr":"53.1199"
    },
    {
      "adv":"-0.8965",
      "id":"bristleback",
      "wr":"53.4594"
    },
    {
      "adv":"-0.9659",
      "id":"drow-ranger",
      "wr":"47.2884"
    },
    {
      "adv":"-1.003",
      "id":"silencer",
      "wr":"46.0762"
    },
    {
      "adv":"-1.0123",
      "id":"dazzle",
      "wr":"47.7787"
    },
    {
      "adv":"-1.0706",
      "id":"axe",
      "wr":"48.7939"
    },
    {
      "adv":"-1.109",
      "id":"undying",
      "wr":"48.9413"
    },
    {
      "adv":"-1.3609",
      "id":"necrophos",
      "wr":"51.8772"
    },
    {
      "adv":"-1.3639",
      "id":"lycan",
      "wr":"47.2009"
    },
    {
      "adv":"-1.4392",
      "id":"templar-assassin",
      "wr":"57.6105"
    },
    {
      "adv":"-1.5677",
      "id":"phantom-assassin",
      "wr":"53.6378"
    },
    {
      "adv":"-1.8584",
      "id":"troll-warlord",
      "wr":"50.7784"
    },
    {
      "adv":"-1.8659",
      "id":"slark",
      "wr":"50.6319"
    }
  ]
}