{
  "id":"shadow-demon",
  "matchups":[
    {
      "adv":"3.8196",
      "id":"meepo",
      "wr":"38.8808"
    },
    {
      "adv":"2.4553",
      "id":"timbersaw",
      "wr":"46.8345"
    },
    {
      "adv":"2.382",
      "id":"weaver",
      "wr":"45.6222"
    },
    {
      "adv":"2.071",
      "id":"phantom-lancer",
      "wr":"44.6948"
    },
    {
      "adv":"2.0377",
      "id":"lone-druid",
      "wr":"41.742"
    },
    {
      "adv":"1.9973",
      "id":"broodmother",
      "wr":"46.4854"
    },
    {
      "adv":"1.8849",
      "id":"riki",
      "wr":"40.0057"
    },
    {
      "adv":"1.8329",
      "id":"lycan",
      "wr":"40.0605"
    },
    {
      "adv":"1.8271",
      "id":"sand-king",
      "wr":"43.7619"
    },
    {
      "adv":"1.8094",
      "id":"underlord",
      "wr":"41.557"
    },
    {
      "adv":"1.7896",
      "id":"earth-spirit",
      "wr":"47.4667"
    },
    {
      "adv":"1.7571",
      "id":"puck",
      "wr":"47.2895"
    },
    {
      "adv":"1.7359",
      "id":"naga-siren",
      "wr":"42.8155"
    },
    {
      "adv":"1.6477",
      "id":"faceless-void",
      "wr":"46.8183"
    },
    {
      "adv":"1.6405",
      "id":"undying",
      "wr":"42.251"
    },
    {
      "adv":"1.5914",
      "id":"brewmaster",
      "wr":"45.0053"
    },
    {
      "adv":"1.4251",
      "id":"queen-of-pain",
      "wr":"49.2063"
    },
    {
      "adv":"1.3948",
      "id":"pudge",
      "wr":"44.3167"
    },
    {
      "adv":"1.3449",
      "id":"void-spirit",
      "wr":"46.4249"
    },
    {
      "adv":"1.3038",
      "id":"ember-spirit",
      "wr":"47.9809"
    },
    {
      "adv":"1.2122",
      "id":"centaur-warrunner",
      "wr":"42.4714"
    },
    {
      "adv":"1.1099",
      "id":"tusk",
      "wr":"46.2149"
    },
    {
      "adv":"1.0686",
      "id":"dawnbreaker",
      "wr":"45.1257"
    },
    {
      "adv":"1.0587",
      "id":"pangolier",
      "wr":"48.8606"
    },
    {
      "adv":"1.0245",
      "id":"chaos-knight",
      "wr":"46.1175"
    },
    {
      "adv":"0.9879",
      "id":"anti-mage",
      "wr":"43.3284"
    },
    {
      "adv":"0.9793",
      "id":"bounty-hunter",
      "wr":"45.3976"
    },
    {
      "adv":"0.9279",
      "id":"beastmaster",
      "wr":"46.9244"
    },
    {
      "adv":"0.8393",
      "id":"razor",
      "wr":"40.5662"
    },
    {
      "adv":"0.8065",
      "id":"earthshaker",
      "wr":"45.666"
    },
    {
      "adv":"0.804",
      "id":"nyx-assassin",
      "wr":"46.0485"
    },
    {
      "adv":"0.8003",
      "id":"crystal-maiden",
      "wr":"44.2377"
    },
    {
      "adv":"0.7896",
      "id":"kunkka",
      "wr":"47.6967"
    },
    {
      "adv":"0.7847",
      "id":"io",
      "wr":"46.0467"
    },
    {
      "adv":"0.775",
      "id":"enchantress",
      "wr":"49.3903"
    },
    {
      "adv":"0.7698",
      "id":"clinkz",
      "wr":"41.9518"
    },
    {
      "adv":"0.7598",
      "id":"morphling",
      "wr":"49.2841"
    },
    {
      "adv":"0.7151",
      "id":"storm-spirit",
      "wr":"49.1481"
    },
    {
      "adv":"0.6158",
      "id":"enigma",
      "wr":"47.9331"
    },
    {
      "adv":"0.6015",
      "id":"keeper-of-the-light",
      "wr":"49.1277"
    },
    {
      "adv":"0.6015",
      "id":"leshrac",
      "wr":"46.8336"
    },
    {
      "adv":"0.5891",
      "id":"tiny",
      "wr":"48.3058"
    },
    {
      "adv":"0.5678",
      "id":"pugna",
      "wr":"49.0467"
    },
    {
      "adv":"0.4731",
      "id":"magnus",
      "wr":"46.5063"
    },
    {
      "adv":"0.466",
      "id":"dark-seer",
      "wr":"44.3795"
    },
    {
      "adv":"0.425",
      "id":"phantom-assassin",
      "wr":"47.5167"
    },
    {
      "adv":"0.3384",
      "id":"vengeful-spirit",
      "wr":"44.7974"
    },
    {
      "adv":"0.3093",
      "id":"spirit-breaker",
      "wr":"46.7991"
    },
    {
      "adv":"0.271",
      "id":"chen",
      "wr":"48.1082"
    },
    {
      "adv":"0.264",
      "id":"sniper",
      "wr":"47.8425"
    },
    {
      "adv":"0.2573",
      "id":"marci",
      "wr":"48.6914"
    },
    {
      "adv":"0.2375",
      "id":"sven",
      "wr":"48.0521"
    },
    {
      "adv":"0.2217",
      "id":"warlock",
      "wr":"44.7634"
    },
    {
      "adv":"0.1622",
      "id":"wraith-king",
      "wr":"45.5658"
    },
    {
      "adv":"0.1621",
      "id":"snapfire",
      "wr":"48.3227"
    },
    {
      "adv":"0.1595",
      "id":"techies",
      "wr":"45.3787"
    },
    {
      "adv":"0.1585",
      "id":"witch-doctor",
      "wr":"44.5841"
    },
    {
      "adv":"0.109",
      "id":"dazzle",
      "wr":"42.7239"
    },
    {
      "adv":"0.0503",
      "id":"alchemist",
      "wr":"49.8997"
    },
    {
      "adv":"0.0471",
      "id":"shadow-shaman",
      "wr":"45.0612"
    },
    {
      "adv":"0.0401",
      "id":"zeus",
      "wr":"45.6508"
    },
    {
      "adv":"0.0397",
      "id":"lina",
      "wr":"48.3738"
    },
    {
      "adv":"0.0322",
      "id":"mars",
      "wr":"48.9559"
    },
    {
      "adv":"0.0307",
      "id":"doom",
      "wr":"49.1856"
    },
    {
      "adv":"0.0212",
      "id":"bloodseeker",
      "wr":"47.1481"
    },
    {
      "adv":"0.021",
      "id":"slark",
      "wr":"44.776"
    },
    {
      "adv":"0.0185",
      "id":"muerta",
      "wr":"51.2892"
    },
    {
      "adv":"0.0046",
      "id":"monkey-king",
      "wr":"50.1378"
    },
    {
      "adv":"-0.127",
      "id":"winter-wyvern",
      "wr":"48.1519"
    },
    {
      "adv":"-0.1331",
      "id":"arc-warden",
      "wr":"42.3655"
    },
    {
      "adv":"-0.1888",
      "id":"phoenix",
      "wr":"47.0548"
    },
    {
      "adv":"-0.2317",
      "id":"jakiro",
      "wr":"44.5279"
    },
    {
      "adv":"-0.2464",
      "id":"juggernaut",
      "wr":"45.2155"
    },
    {
      "adv":"-0.264",
      "id":"silencer",
      "wr":"41.5152"
    },
    {
      "adv":"-0.2663",
      "id":"drow-ranger",
      "wr":"42.7044"
    },
    {
      "adv":"-0.3215",
      "id":"tidehunter",
      "wr":"45.9909"
    },
    {
      "adv":"-0.3243",
      "id":"spectre",
      "wr":"41.9713"
    },
    {
      "adv":"-0.3937",
      "id":"visage",
      "wr":"44.4004"
    },
    {
      "adv":"-0.3975",
      "id":"outworld-destroyer",
      "wr":"46.2742"
    },
    {
      "adv":"-0.4804",
      "id":"hoodwink",
      "wr":"47.385"
    },
    {
      "adv":"-0.4992",
      "id":"shadow-fiend",
      "wr":"46.0367"
    },
    {
      "adv":"-0.5707",
      "id":"lion",
      "wr":"49.6922"
    },
    {
      "adv":"-0.5788",
      "id":"medusa",
      "wr":"47.9844"
    },
    {
      "adv":"-0.6064",
      "id":"mirana",
      "wr":"44.1261"
    },
    {
      "adv":"-0.6386",
      "id":"ancient-apparition",
      "wr":"45.1902"
    },
    {
      "adv":"-0.6588",
      "id":"natures-prophet",
      "wr":"51.3884"
    },
    {
      "adv":"-0.7058",
      "id":"invoker",
      "wr":"49.2753"
    },
    {
      "adv":"-0.7222",
      "id":"bristleback",
      "wr":"48.9888"
    },
    {
      "adv":"-0.7524",
      "id":"troll-warlord",
      "wr":"45.5621"
    },
    {
      "adv":"-0.7723",
      "id":"dark-willow",
      "wr":"47.0016"
    },
    {
      "adv":"-0.784",
      "id":"bane",
      "wr":"49.6715"
    },
    {
      "adv":"-0.7851",
      "id":"templar-assassin",
      "wr":"52.4731"
    },
    {
      "adv":"-0.7977",
      "id":"primal-beast",
      "wr":"49.142"
    },
    {
      "adv":"-0.805",
      "id":"terrorblade",
      "wr":"52.235"
    },
    {
      "adv":"-0.8503",
      "id":"treant-protector",
      "wr":"43.0724"
    },
    {
      "adv":"-0.8607",
      "id":"axe",
      "wr":"44.5658"
    },
    {
      "adv":"-0.895",
      "id":"venomancer",
      "wr":"47.1245"
    },
    {
      "adv":"-0.8997",
      "id":"tinker",
      "wr":"44.8879"
    },
    {
      "adv":"-0.9347",
      "id":"huskar",
      "wr":"47.0558"
    },
    {
      "adv":"-0.944",
      "id":"ogre-magi",
      "wr":"47.9657"
    },
    {
      "adv":"-0.9459",
      "id":"lifestealer",
      "wr":"47.6294"
    },
    {
      "adv":"-0.976",
      "id":"death-prophet",
      "wr":"47.0761"
    },
    {
      "adv":"-0.9981",
      "id":"clockwerk",
      "wr":"47.1273"
    },
    {
      "adv":"-1.0041",
      "id":"rubick",
      "wr":"50.347"
    },
    {
      "adv":"-1.0122",
      "id":"elder-titan",
      "wr":"48.8431"
    },
    {
      "adv":"-1.0928",
      "id":"slardar",
      "wr":"45.7591"
    },
    {
      "adv":"-1.0934",
      "id":"luna",
      "wr":"47.119"
    },
    {
      "adv":"-1.1609",
      "id":"skywrath-mage",
      "wr":"46.3876"
    },
    {
      "adv":"-1.2181",
      "id":"night-stalker",
      "wr":"46.8802"
    },
    {
      "adv":"-1.2319",
      "id":"disruptor",
      "wr":"47.1304"
    },
    {
      "adv":"-1.2929",
      "id":"viper",
      "wr":"49.1911"
    },
    {
      "adv":"-1.3088",
      "id":"gyrocopter",
      "wr":"47.1337"
    },
    {
      "adv":"-1.4811",
      "id":"ursa",
      "wr":"47.3541"
    },
    {
      "adv":"-1.5756",
      "id":"dragon-knight",
      "wr":"50.6753"
    },
    {
      "adv":"-1.5778",
      "id":"lich",
      "wr":"46.1609"
    },
    {
      "adv":"-1.658",
      "id":"windranger",
      "wr":"48.8186"
    },
    {
      "adv":"-1.7301",
      "id":"batrider",
      "wr":"53.4121"
    },
    {
      "adv":"-1.8141",
      "id":"necrophos",
      "wr":"48.1049"
    },
    {
      "adv":"-1.9625",
      "id":"oracle",
      "wr":"48.6212"
    },
    {
      "adv":"-1.9799",
      "id":"grimstroke",
      "wr":"49.979"
    },
    {
      "adv":"-2.4035",
      "id":"legion-commander",
      "wr":"44.7871"
    },
    {
      "adv":"-2.8063",
      "id":"abaddon",
      "wr":"48.1101"
    },
    {
      "adv":"-3.9563",
      "id":"omniknight",
      "wr":"46.2292"
    }
  ]
}