{
  "id":"treant-protector",
  "matchups":[
    {
      "adv":"3.3708",
      "id":"batrider",
      "wr":"56.8099"
    },
    {
      "adv":"2.9128",
      "id":"phoenix",
      "wr":"51.9836"
    },
    {
      "adv":"2.5827",
      "id":"muerta",
      "wr":"57.0649"
    },
    {
      "adv":"2.447",
      "id":"huskar",
      "wr":"51.7119"
    },
    {
      "adv":"2.3736",
      "id":"leshrac",
      "wr":"53.1443"
    },
    {
      "adv":"2.3405",
      "id":"slark",
      "wr":"50.5088"
    },
    {
      "adv":"2.2933",
      "id":"death-prophet",
      "wr":"51.8282"
    },
    {
      "adv":"2.2836",
      "id":"timbersaw",
      "wr":"55.3628"
    },
    {
      "adv":"1.7811",
      "id":"viper",
      "wr":"54.3139"
    },
    {
      "adv":"1.7597",
      "id":"keeper-of-the-light",
      "wr":"56.2197"
    },
    {
      "adv":"1.7287",
      "id":"juggernaut",
      "wr":"51.2853"
    },
    {
      "adv":"1.6724",
      "id":"magnus",
      "wr":"53.4129"
    },
    {
      "adv":"1.6113",
      "id":"brewmaster",
      "wr":"53.007"
    },
    {
      "adv":"1.5055",
      "id":"earth-spirit",
      "wr":"55.998"
    },
    {
      "adv":"1.4858",
      "id":"broodmother",
      "wr":"55.2255"
    },
    {
      "adv":"1.4527",
      "id":"primal-beast",
      "wr":"55.1301"
    },
    {
      "adv":"1.4219",
      "id":"weaver",
      "wr":"54.6614"
    },
    {
      "adv":"1.4143",
      "id":"oracle",
      "wr":"53.3092"
    },
    {
      "adv":"1.3876",
      "id":"necrophos",
      "wr":"53.0332"
    },
    {
      "adv":"1.3363",
      "id":"pugna",
      "wr":"56.5086"
    },
    {
      "adv":"1.3296",
      "id":"shadow-demon",
      "wr":"56.9275"
    },
    {
      "adv":"1.316",
      "id":"morphling",
      "wr":"57.06"
    },
    {
      "adv":"1.2569",
      "id":"ancient-apparition",
      "wr":"51.2153"
    },
    {
      "adv":"1.2408",
      "id":"enigma",
      "wr":"55.4802"
    },
    {
      "adv":"1.2195",
      "id":"ursa",
      "wr":"52.755"
    },
    {
      "adv":"1.2084",
      "id":"mars",
      "wr":"56.032"
    },
    {
      "adv":"1.1728",
      "id":"venomancer",
      "wr":"53.0991"
    },
    {
      "adv":"1.1644",
      "id":"snapfire",
      "wr":"55.5403"
    },
    {
      "adv":"1.13",
      "id":"bristleback",
      "wr":"55.3108"
    },
    {
      "adv":"1.0803",
      "id":"undying",
      "wr":"50.6252"
    },
    {
      "adv":"1.0433",
      "id":"lina",
      "wr":"55.5999"
    },
    {
      "adv":"0.9038",
      "id":"dark-seer",
      "wr":"51.855"
    },
    {
      "adv":"0.8832",
      "id":"pudge",
      "wr":"52.7256"
    },
    {
      "adv":"0.8526",
      "id":"io",
      "wr":"54.0623"
    },
    {
      "adv":"0.8245",
      "id":"puck",
      "wr":"56.4371"
    },
    {
      "adv":"0.7867",
      "id":"anti-mage",
      "wr":"51.3628"
    },
    {
      "adv":"0.7086",
      "id":"crystal-maiden",
      "wr":"52.2496"
    },
    {
      "adv":"0.7055",
      "id":"grimstroke",
      "wr":"55.4952"
    },
    {
      "adv":"0.6869",
      "id":"tinker",
      "wr":"51.2121"
    },
    {
      "adv":"0.6803",
      "id":"omniknight",
      "wr":"49.3446"
    },
    {
      "adv":"0.6651",
      "id":"enchantress",
      "wr":"57.7742"
    },
    {
      "adv":"0.6567",
      "id":"lich",
      "wr":"51.9085"
    },
    {
      "adv":"0.6559",
      "id":"dawnbreaker",
      "wr":"53.5597"
    },
    {
      "adv":"0.6403",
      "id":"techies",
      "wr":"52.8926"
    },
    {
      "adv":"0.6385",
      "id":"storm-spirit",
      "wr":"57.4973"
    },
    {
      "adv":"0.6204",
      "id":"bane",
      "wr":"56.4868"
    },
    {
      "adv":"0.6101",
      "id":"phantom-lancer",
      "wr":"54.1759"
    },
    {
      "adv":"0.6049",
      "id":"dark-willow",
      "wr":"53.6692"
    },
    {
      "adv":"0.6046",
      "id":"faceless-void",
      "wr":"55.9601"
    },
    {
      "adv":"0.5869",
      "id":"terrorblade",
      "wr":"59.2666"
    },
    {
      "adv":"0.5739",
      "id":"invoker",
      "wr":"56.2594"
    },
    {
      "adv":"0.5515",
      "id":"sand-king",
      "wr":"52.9772"
    },
    {
      "adv":"0.5498",
      "id":"chen",
      "wr":"56.0364"
    },
    {
      "adv":"0.5399",
      "id":"underlord",
      "wr":"50.6282"
    },
    {
      "adv":"0.5388",
      "id":"queen-of-pain",
      "wr":"58.4017"
    },
    {
      "adv":"0.4675",
      "id":"outworld-destroyer",
      "wr":"53.4403"
    },
    {
      "adv":"0.442",
      "id":"rubick",
      "wr":"57.2626"
    },
    {
      "adv":"0.4366",
      "id":"monkey-king",
      "wr":"58.0282"
    },
    {
      "adv":"0.4295",
      "id":"nyx-assassin",
      "wr":"54.477"
    },
    {
      "adv":"0.394",
      "id":"tidehunter",
      "wr":"53.2675"
    },
    {
      "adv":"0.3939",
      "id":"alchemist",
      "wr":"57.817"
    },
    {
      "adv":"0.3826",
      "id":"skywrath-mage",
      "wr":"52.8767"
    },
    {
      "adv":"0.374",
      "id":"winter-wyvern",
      "wr":"55.8265"
    },
    {
      "adv":"0.3607",
      "id":"doom",
      "wr":"57.1263"
    },
    {
      "adv":"0.3335",
      "id":"jakiro",
      "wr":"51.8781"
    },
    {
      "adv":"0.3292",
      "id":"gyrocopter",
      "wr":"53.5511"
    },
    {
      "adv":"0.3046",
      "id":"abaddon",
      "wr":"52.9888"
    },
    {
      "adv":"0.3009",
      "id":"warlock",
      "wr":"52.6266"
    },
    {
      "adv":"0.2868",
      "id":"bounty-hunter",
      "wr":"54.1029"
    },
    {
      "adv":"0.2824",
      "id":"witch-doctor",
      "wr":"52.4004"
    },
    {
      "adv":"0.2816",
      "id":"windranger",
      "wr":"55.0806"
    },
    {
      "adv":"0.2371",
      "id":"arc-warden",
      "wr":"49.7355"
    },
    {
      "adv":"0.1998",
      "id":"zeus",
      "wr":"53.4916"
    },
    {
      "adv":"0.1685",
      "id":"troll-warlord",
      "wr":"52.5752"
    },
    {
      "adv":"0.1465",
      "id":"sniper",
      "wr":"56.0934"
    },
    {
      "adv":"0.0964",
      "id":"void-spirit",
      "wr":"55.7919"
    },
    {
      "adv":"0.0942",
      "id":"earthshaker",
      "wr":"54.3798"
    },
    {
      "adv":"0.0694",
      "id":"clockwerk",
      "wr":"54.1259"
    },
    {
      "adv":"0.0313",
      "id":"elder-titan",
      "wr":"55.9413"
    },
    {
      "adv":"0.0214",
      "id":"pangolier",
      "wr":"58.209"
    },
    {
      "adv":"0.0167",
      "id":"silencer",
      "wr":"48.9364"
    },
    {
      "adv":"0.0033",
      "id":"drow-ranger",
      "wr":"50.2172"
    },
    {
      "adv":"-0.0403",
      "id":"beastmaster",
      "wr":"56.1648"
    },
    {
      "adv":"-0.1206",
      "id":"disruptor",
      "wr":"54.0942"
    },
    {
      "adv":"-0.2226",
      "id":"kunkka",
      "wr":"56.8781"
    },
    {
      "adv":"-0.2453",
      "id":"lion",
      "wr":"57.6303"
    },
    {
      "adv":"-0.2605",
      "id":"ogre-magi",
      "wr":"55.4242"
    },
    {
      "adv":"-0.3109",
      "id":"dazzle",
      "wr":"50.933"
    },
    {
      "adv":"-0.325",
      "id":"bloodseeker",
      "wr":"55.5857"
    },
    {
      "adv":"-0.341",
      "id":"mirana",
      "wr":"51.7332"
    },
    {
      "adv":"-0.3428",
      "id":"natures-prophet",
      "wr":"59.4742"
    },
    {
      "adv":"-0.398",
      "id":"hoodwink",
      "wr":"55.4247"
    },
    {
      "adv":"-0.41",
      "id":"visage",
      "wr":"52.3118"
    },
    {
      "adv":"-0.4223",
      "id":"shadow-fiend",
      "wr":"53.96"
    },
    {
      "adv":"-0.4313",
      "id":"vengeful-spirit",
      "wr":"53.5315"
    },
    {
      "adv":"-0.4547",
      "id":"ember-spirit",
      "wr":"57.9646"
    },
    {
      "adv":"-0.4741",
      "id":"marci",
      "wr":"57.6907"
    },
    {
      "adv":"-0.527",
      "id":"tiny",
      "wr":"57.6396"
    },
    {
      "adv":"-0.5399",
      "id":"naga-siren",
      "wr":"53.0122"
    },
    {
      "adv":"-0.5701",
      "id":"medusa",
      "wr":"56.091"
    },
    {
      "adv":"-0.5724",
      "id":"luna",
      "wr":"54.6383"
    },
    {
      "adv":"-0.5905",
      "id":"dragon-knight",
      "wr":"57.9578"
    },
    {
      "adv":"-0.6728",
      "id":"spirit-breaker",
      "wr":"55.8554"
    },
    {
      "adv":"-0.6903",
      "id":"shadow-shaman",
      "wr":"53.7256"
    },
    {
      "adv":"-0.7357",
      "id":"night-stalker",
      "wr":"54.4323"
    },
    {
      "adv":"-0.7657",
      "id":"riki",
      "wr":"50.2667"
    },
    {
      "adv":"-0.8948",
      "id":"chaos-knight",
      "wr":"56.1181"
    },
    {
      "adv":"-0.9209",
      "id":"centaur-warrunner",
      "wr":"52.4426"
    },
    {
      "adv":"-0.9744",
      "id":"lone-druid",
      "wr":"52.6379"
    },
    {
      "adv":"-0.9807",
      "id":"clinkz",
      "wr":"51.4382"
    },
    {
      "adv":"-1.0506",
      "id":"sven",
      "wr":"57.5036"
    },
    {
      "adv":"-1.0626",
      "id":"slardar",
      "wr":"53.6888"
    },
    {
      "adv":"-1.0641",
      "id":"lycan",
      "wr":"50.7"
    },
    {
      "adv":"-1.1766",
      "id":"tusk",
      "wr":"56.5424"
    },
    {
      "adv":"-1.1974",
      "id":"razor",
      "wr":"50.1681"
    },
    {
      "adv":"-1.2038",
      "id":"meepo",
      "wr":"51.7212"
    },
    {
      "adv":"-1.3704",
      "id":"lifestealer",
      "wr":"56.1424"
    },
    {
      "adv":"-1.4009",
      "id":"axe",
      "wr":"52.9662"
    },
    {
      "adv":"-1.4125",
      "id":"phantom-assassin",
      "wr":"57.3829"
    },
    {
      "adv":"-1.7756",
      "id":"legion-commander",
      "wr":"52.0204"
    },
    {
      "adv":"-1.8777",
      "id":"templar-assassin",
      "wr":"62.0391"
    },
    {
      "adv":"-1.9371",
      "id":"wraith-king",
      "wr":"55.6558"
    },
    {
      "adv":"-2.4989",
      "id":"spectre",
      "wr":"51.8381"
    }
  ]
}