{"id":"underlord","matchups":[{"adv":"5.9909","id":"rubick","wr":"49.6769"},{"adv":"5.2308","id":"juggernaut","wr":"41.8921"},{"adv":"3.3663","id":"sniper","wr":"47.2118"},{"adv":"3.0992","id":"ursa","wr":"47.2467"},{"adv":"2.4431","id":"huskar","wr":"48.4553"},{"adv":"2.0292","id":"doom","wr":"53.7238"},{"adv":"2.0289","id":"lifestealer","wr":"49.3708"},{"adv":"2.0131","id":"outworld-destroyer","wr":"47.9378"},{"adv":"1.8106","id":"pudge","wr":"49.0252"},{"adv":"1.773","id":"pugna","wr":"53.091"},{"adv":"1.6717","id":"witch-doctor","wr":"50.1125"},{"adv":"1.6349","id":"clinkz","wr":"48.3755"},{"adv":"1.6042","id":"bristleback","wr":"48.93"},{"adv":"1.5457","id":"snapfire","wr":"53.7106"},{"adv":"1.5436","id":"batrider","wr":"54.6908"},{"adv":"1.4523","id":"tinker","wr":"51.6459"},{"adv":"1.3578","id":"enigma","wr":"49.1457"},{"adv":"1.2205","id":"bane","wr":"51.3096"},{"adv":"1.1792","id":"leshrac","wr":"53.8474"},{"adv":"1.1461","id":"dark-seer","wr":"50.4426"},{"adv":"1.143","id":"invoker","wr":"52.6043"},{"adv":"1.1114","id":"shadow-shaman","wr":"48.4538"},{"adv":"1.05","id":"keeper-of-the-light","wr":"51.6458"},{"adv":"1.0397","id":"arc-warden","wr":"45.5401"},{"adv":"0.9992","id":"monkey-king","wr":"55.7116"},{"adv":"0.9962","id":"timbersaw","wr":"54.0131"},{"adv":"0.9757","id":"oracle","wr":"52.0312"},{"adv":"0.9693","id":"viper","wr":"51.1952"},{"adv":"0.9673","id":"shadow-fiend","wr":"49.5423"},{"adv":"0.9503","id":"drow-ranger","wr":"48.4148"},{"adv":"0.9164","id":"anti-mage","wr":"52.9122"},{"adv":"0.9044","id":"ancient-apparition","wr":"49.9428"},{"adv":"0.8543","id":"bounty-hunter","wr":"50.3878"},{"adv":"0.736","id":"lina","wr":"53.2185"},{"adv":"0.7355","id":"hoodwink","wr":"50.4842"},{"adv":"0.7299","id":"enchantress","wr":"51.9937"},{"adv":"0.6811","id":"crystal-maiden","wr":"47.5032"},{"adv":"0.6426","id":"skywrath-mage","wr":"48.5435"},{"adv":"0.6278","id":"bloodseeker","wr":"49.6838"},{"adv":"0.5419","id":"silencer","wr":"48.2779"},{"adv":"0.5413","id":"brewmaster","wr":"49.012"},{"adv":"0.5035","id":"jakiro","wr":"48.4461"},{"adv":"0.5024","id":"faceless-void","wr":"52.1427"},{"adv":"0.5015","id":"alchemist","wr":"49.477"},{"adv":"0.4851","id":"razor","wr":"50.7697"},{"adv":"0.476","id":"death-prophet","wr":"53.9761"},{"adv":"0.4743","id":"slark","wr":"52.4248"},{"adv":"0.4052","id":"windranger","wr":"50.5051"},{"adv":"0.3815","id":"sven","wr":"53.3956"},{"adv":"0.3256","id":"techies","wr":"51.2998"},{"adv":"0.3201","id":"lich","wr":"50.6545"},{"adv":"0.3102","id":"night-stalker","wr":"48.6846"},{"adv":"0.2321","id":"magnus","wr":"53.6989"},{"adv":"0.2319","id":"venomancer","wr":"48.9019"},{"adv":"0.1568","id":"elder-titan","wr":"52.8119"},{"adv":"0.0499","id":"slardar","wr":"51.942"},{"adv":"-0.0034","id":"pangolier","wr":"54.8505"},{"adv":"-0.0356","id":"dazzle","wr":"47.7373"},{"adv":"-0.0512","id":"morphling","wr":"51.6948"},{"adv":"-0.1208","id":"nyx-assassin","wr":"51.0747"},{"adv":"-0.1481","id":"grimstroke","wr":"54.0445"},{"adv":"-0.2012","id":"warlock","wr":"47.5395"},{"adv":"-0.2242","id":"legion-commander","wr":"51.1698"},{"adv":"-0.2787","id":"disruptor","wr":"52.5719"},{"adv":"-0.2825","id":"phoenix","wr":"53.3602"},{"adv":"-0.4395","id":"broodmother","wr":"56.0975"},{"adv":"-0.4743","id":"zeus","wr":"48.7638"},{"adv":"-0.5112","id":"mars","wr":"55.0375"},{"adv":"-0.5597","id":"earth-spirit","wr":"54.6037"},{"adv":"-0.5854","id":"tidehunter","wr":"54.1178"},{"adv":"-0.6415","id":"earthshaker","wr":"52.2012"},{"adv":"-0.6752","id":"winter-wyvern","wr":"50.3622"},{"adv":"-0.6821","id":"gyrocopter","wr":"52.7434"},{"adv":"-0.6968","id":"undying","wr":"50.1382"},{"adv":"-0.7257","id":"vengeful-spirit","wr":"50.1234"},{"adv":"-0.7312","id":"omniknight","wr":"49.5682"},{"adv":"-0.7345","id":"lion","wr":"55.3296"},{"adv":"-0.7638","id":"weaver","wr":"52.7475"},{"adv":"-0.7674","id":"clockwerk","wr":"52.6148"},{"adv":"-0.8166","id":"ogre-magi","wr":"50.4752"},{"adv":"-0.8211","id":"shadow-demon","wr":"54.7887"},{"adv":"-0.8635","id":"kunkka","wr":"54.9977"},{"adv":"-0.881","id":"necrophos","wr":"51.2579"},{"adv":"-0.9046","id":"queen-of-pain","wr":"55.7199"},{"adv":"-0.9488","id":"io","wr":"52.7497"},{"adv":"-0.9887","id":"phantom-assassin","wr":"53.8205"},{"adv":"-0.9898","id":"mirana","wr":"50.7353"},{"adv":"-1.0529","id":"beastmaster","wr":"52.2545"},{"adv":"-1.0722","id":"natures-prophet","wr":"57.926"},{"adv":"-1.0966","id":"luna","wr":"51.7432"},{"adv":"-1.2838","id":"treant-protector","wr":"51.3978"},{"adv":"-1.2873","id":"abaddon","wr":"51.3449"},{"adv":"-1.2875","id":"troll-warlord","wr":"52.743"},{"adv":"-1.3396","id":"dawnbreaker","wr":"49.0403"},{"adv":"-1.4082","id":"axe","wr":"49.0599"},{"adv":"-1.5491","id":"marci","wr":"53.3994"},{"adv":"-1.5596","id":"templar-assassin","wr":"56.047"},{"adv":"-1.5622","id":"storm-spirit","wr":"59.1812"},{"adv":"-1.563","id":"dark-willow","wr":"54.534"},{"adv":"-1.6999","id":"tusk","wr":"55.2622"},{"adv":"-1.7035","id":"chen","wr":"50.8416"},{"adv":"-1.8017","id":"visage","wr":"47.0661"},{"adv":"-1.8867","id":"puck","wr":"54.089"},{"adv":"-2.0082","id":"tiny","wr":"53.6754"},{"adv":"-2.0442","id":"dragon-knight","wr":"56.2587"},{"adv":"-2.0919","id":"ember-spirit","wr":"59.1741"},{"adv":"-2.0959","id":"sand-king","wr":"53.0327"},{"adv":"-2.2238","id":"void-spirit","wr":"53.2332"},{"adv":"-2.3149","id":"primal-beast","wr":"58.3958"},{"adv":"-2.3948","id":"centaur-warrunner","wr":"51.1384"},{"adv":"-2.6433","id":"spectre","wr":"50.6489"},{"adv":"-2.7038","id":"terrorblade","wr":"58.81"},{"adv":"-2.7278","id":"chaos-knight","wr":"53.4196"},{"adv":"-2.8086","id":"riki","wr":"51.4781"},{"adv":"-3.6162","id":"medusa","wr":"55.6169"},{"adv":"-3.6712","id":"spirit-breaker","wr":"56.4548"},{"adv":"-3.994","id":"lycan","wr":"53.7677"},{"adv":"-4.1642","id":"lone-druid","wr":"52.8906"},{"adv":"-4.814","id":"wraith-king","wr":"53.9785"},{"adv":"-5.8044","id":"meepo","wr":"54.405"},{"adv":"-6.0625","id":"phantom-lancer","wr":"57.48"},{"adv":"-7.6076","id":"naga-siren","wr":"57.6779"}]}