{"id":"warlock","matchups":[{"adv":"4.2489","id":"broodmother","wr":"54.1677"},{"adv":"3.1839","id":"bristleback","wr":"50.1296"},{"adv":"2.3853","id":"huskar","wr":"51.2209"},{"adv":"2.2578","id":"slark","wr":"53.4651"},{"adv":"2.0626","id":"natures-prophet","wr":"57.6943"},{"adv":"1.9424","id":"tidehunter","wr":"54.3873"},{"adv":"1.8299","id":"shadow-fiend","wr":"51.4354"},{"adv":"1.8006","id":"sven","wr":"54.7621"},{"adv":"1.7483","id":"weaver","wr":"53.042"},{"adv":"1.6361","id":"shadow-demon","wr":"55.0931"},{"adv":"1.6065","id":"slardar","wr":"53.1529"},{"adv":"1.5819","id":"viper","wr":"53.3531"},{"adv":"1.488","id":"troll-warlord","wr":"52.7059"},{"adv":"1.3564","id":"lina","wr":"55.4058"},{"adv":"1.3078","id":"alchemist","wr":"51.3883"},{"adv":"1.2879","id":"ursa","wr":"51.6995"},{"adv":"1.2548","id":"enchantress","wr":"54.2341"},{"adv":"1.246","id":"leshrac","wr":"56.5973"},{"adv":"1.2409","id":"bounty-hunter","wr":"52.7407"},{"adv":"1.1713","id":"faceless-void","wr":"54.2616"},{"adv":"1.1308","id":"oracle","wr":"54.6633"},{"adv":"1.1135","id":"sniper","wr":"51.9699"},{"adv":"1.0848","id":"brewmaster","wr":"51.1633"},{"adv":"1.0549","id":"marci","wr":"53.6413"},{"adv":"1.0472","id":"legion-commander","wr":"52.6836"},{"adv":"1.0367","id":"monkey-king","wr":"58.5264"},{"adv":"0.9365","id":"batrider","wr":"58.1749"},{"adv":"0.9149","id":"omniknight","wr":"50.5971"},{"adv":"0.9123","id":"morphling","wr":"53.489"},{"adv":"0.9003","id":"doom","wr":"57.6866"},{"adv":"0.8688","id":"pangolier","wr":"56.8076"},{"adv":"0.8682","id":"lycan","wr":"51.5618"},{"adv":"0.8265","id":"lich","wr":"52.898"},{"adv":"0.7969","id":"primal-beast","wr":"58.1157"},{"adv":"0.7804","id":"io","wr":"53.7689"},{"adv":"0.7606","id":"phoenix","wr":"55.1046"},{"adv":"0.708","id":"jakiro","wr":"50.9454"},{"adv":"0.7062","id":"invoker","wr":"55.7913"},{"adv":"0.6874","id":"ancient-apparition","wr":"52.8893"},{"adv":"0.6797","id":"keeper-of-the-light","wr":"54.782"},{"adv":"0.6729","id":"undying","wr":"51.5035"},{"adv":"0.6463","id":"clinkz","wr":"52.0748"},{"adv":"0.5979","id":"chen","wr":"51.2036"},{"adv":"0.5722","id":"snapfire","wr":"57.4867"},{"adv":"0.5424","id":"phantom-assassin","wr":"55.162"},{"adv":"0.523","id":"ember-spirit","wr":"59.481"},{"adv":"0.5206","id":"crystal-maiden","wr":"50.3427"},{"adv":"0.5197","id":"earthshaker","wr":"53.8227"},{"adv":"0.5143","id":"bane","wr":"54.8"},{"adv":"0.4934","id":"pugna","wr":"57.1795"},{"adv":"0.4911","id":"kunkka","wr":"56.4626"},{"adv":"0.4423","id":"drow-ranger","wr":"51.5893"},{"adv":"0.4316","id":"death-prophet","wr":"56.8317"},{"adv":"0.4095","id":"dark-willow","wr":"55.3532"},{"adv":"0.3733","id":"magnus","wr":"56.3602"},{"adv":"0.3712","id":"lifestealer","wr":"53.7166"},{"adv":"0.3468","id":"razor","wr":"53.6515"},{"adv":"0.3312","id":"phantom-lancer","wr":"53.9031"},{"adv":"0.3132","id":"medusa","wr":"54.5263"},{"adv":"0.3106","id":"outworld-destroyer","wr":"52.3129"},{"adv":"0.2605","id":"rubick","wr":"57.9019"},{"adv":"0.2597","id":"underlord","wr":"52.4601"},{"adv":"0.2492","id":"templar-assassin","wr":"57.0668"},{"adv":"0.1006","id":"skywrath-mage","wr":"51.7582"},{"adv":"0.0921","id":"tusk","wr":"56.2905"},{"adv":"0.092","id":"juggernaut","wr":"49.1649"},{"adv":"0.0769","id":"grimstroke","wr":"56.6306"},{"adv":"0.0493","id":"storm-spirit","wr":"60.4558"},{"adv":"0.0451","id":"lone-druid","wr":"51.3591"},{"adv":"0.0264","id":"treant-protector","wr":"52.8219"},{"adv":"-0.0014","id":"queen-of-pain","wr":"57.6666"},{"adv":"-0.038","id":"riki","wr":"51.4226"},{"adv":"-0.1036","id":"abaddon","wr":"52.8873"},{"adv":"-0.1053","id":"windranger","wr":"53.7209"},{"adv":"-0.1335","id":"dawnbreaker","wr":"50.5717"},{"adv":"-0.1478","id":"mirana","wr":"52.6433"},{"adv":"-0.1539","id":"sand-king","wr":"53.8728"},{"adv":"-0.1552","id":"nyx-assassin","wr":"53.8494"},{"adv":"-0.1589","id":"earth-spirit","wr":"57.0128"},{"adv":"-0.1749","id":"night-stalker","wr":"51.8623"},{"adv":"-0.1924","id":"anti-mage","wr":"56.7738"},{"adv":"-0.2342","id":"gyrocopter","wr":"55.0768"},{"adv":"-0.2717","id":"disruptor","wr":"55.343"},{"adv":"-0.2804","id":"spirit-breaker","wr":"55.9441"},{"adv":"-0.3599","id":"dazzle","wr":"50.734"},{"adv":"-0.3924","id":"techies","wr":"54.7522"},{"adv":"-0.417","id":"bloodseeker","wr":"53.4357"},{"adv":"-0.4549","id":"venomancer","wr":"52.2747"},{"adv":"-0.4705","id":"pudge","wr":"53.7428"},{"adv":"-0.5016","id":"witch-doctor","wr":"54.9087"},{"adv":"-0.5163","id":"winter-wyvern","wr":"52.9307"},{"adv":"-0.6196","id":"tinker","wr":"56.4841"},{"adv":"-0.6202","id":"clockwerk","wr":"55.2398"},{"adv":"-0.6259","id":"tiny","wr":"55.1135"},{"adv":"-0.6616","id":"shadow-shaman","wr":"52.8369"},{"adv":"-0.6618","id":"void-spirit","wr":"54.4723"},{"adv":"-0.6976","id":"silencer","wr":"52.1412"},{"adv":"-0.7119","id":"hoodwink","wr":"54.6283"},{"adv":"-0.7143","id":"puck","wr":"55.7351"},{"adv":"-0.7354","id":"ogre-magi","wr":"53.1153"},{"adv":"-0.7929","id":"lion","wr":"58.195"},{"adv":"-0.847","id":"naga-siren","wr":"53.5925"},{"adv":"-0.9675","id":"luna","wr":"54.3571"},{"adv":"-1.0212","id":"dragon-knight","wr":"58.0653"},{"adv":"-1.0474","id":"visage","wr":"48.9178"},{"adv":"-1.0645","id":"chaos-knight","wr":"54.5353"},{"adv":"-1.0867","id":"wraith-king","wr":"53.1148"},{"adv":"-1.1029","id":"elder-titan","wr":"56.8965"},{"adv":"-1.1089","id":"vengeful-spirit","wr":"53.2225"},{"adv":"-1.1208","id":"enigma","wr":"54.3366"},{"adv":"-1.1818","id":"timbersaw","wr":"58.993"},{"adv":"-1.2944","id":"necrophos","wr":"54.3892"},{"adv":"-1.5686","id":"zeus","wr":"52.472"},{"adv":"-1.6294","id":"mars","wr":"58.9617"},{"adv":"-1.6484","id":"beastmaster","wr":"55.6317"},{"adv":"-1.934","id":"dark-seer","wr":"56.3284"},{"adv":"-2.0087","id":"axe","wr":"52.3007"},{"adv":"-2.1238","id":"arc-warden","wr":"51.3337"},{"adv":"-2.1291","id":"centaur-warrunner","wr":"53.5902"},{"adv":"-2.5756","id":"terrorblade","wr":"61.565"},{"adv":"-3.3151","id":"spectre","wr":"54.0179"},{"adv":"-5.3751","id":"meepo","wr":"56.7038"}]}