{"id":"queen-of-pain","matchups":[{"adv":"2.4228","id":"meepo","wr":"40.9903"},{"adv":"2.2353","id":"huskar","wr":"43.6127"},{"adv":"2.1415","id":"puck","wr":"45.1789"},{"adv":"2.109","id":"medusa","wr":"44.9976"},{"adv":"1.985","id":"pugna","wr":"48.0017"},{"adv":"1.9643","id":"legion-commander","wr":"44.0581"},{"adv":"1.9468","id":"abaddon","wr":"43.0135"},{"adv":"1.4469","id":"naga-siren","wr":"43.4819"},{"adv":"1.3567","id":"ember-spirit","wr":"51.0411"},{"adv":"1.3567","id":"lone-druid","wr":"42.2121"},{"adv":"1.3068","id":"lina","wr":"47.7716"},{"adv":"1.2822","id":"oracle","wr":"46.7779"},{"adv":"1.2304","id":"night-stalker","wr":"42.6481"},{"adv":"1.2148","id":"shadow-fiend","wr":"44.2708"},{"adv":"1.1405","id":"templar-assassin","wr":"48.5119"},{"adv":"0.9482","id":"faceless-void","wr":"46.769"},{"adv":"0.9277","id":"enigma","wr":"44.551"},{"adv":"0.9142","id":"slark","wr":"47.064"},{"adv":"0.8887","id":"witch-doctor","wr":"45.8735"},{"adv":"0.8862","id":"anti-mage","wr":"48.0403"},{"adv":"0.8602","id":"omniknight","wr":"42.8402"},{"adv":"0.7704","id":"troll-warlord","wr":"45.703"},{"adv":"0.7445","id":"techies","wr":"45.9123"},{"adv":"0.7296","id":"viper","wr":"46.4569"},{"adv":"0.6597","id":"tidehunter","wr":"47.9696"},{"adv":"0.6358","id":"nyx-assassin","wr":"45.2877"},{"adv":"0.6268","id":"underlord","wr":"44.2893"},{"adv":"0.564","id":"riki","wr":"43.027"},{"adv":"0.5559","id":"clinkz","wr":"44.3814"},{"adv":"0.4585","id":"skywrath-mage","wr":"43.6457"},{"adv":"0.455","id":"chaos-knight","wr":"45.2934"},{"adv":"0.4345","id":"natures-prophet","wr":"51.7002"},{"adv":"0.4106","id":"tiny","wr":"46.3842"},{"adv":"0.3939","id":"enchantress","wr":"47.3921"},{"adv":"0.3721","id":"io","wr":"46.4642"},{"adv":"0.3661","id":"luna","wr":"45.2904"},{"adv":"0.3532","id":"shadow-shaman","wr":"44.1042"},{"adv":"0.3526","id":"morphling","wr":"46.33"},{"adv":"0.3248","id":"disruptor","wr":"47.0178"},{"adv":"0.2953","id":"drow-ranger","wr":"43.96"},{"adv":"0.2301","id":"kunkka","wr":"49.0556"},{"adv":"0.192","id":"lycan","wr":"44.4978"},{"adv":"0.17","id":"death-prophet","wr":"49.4254"},{"adv":"0.1692","id":"terrorblade","wr":"51.135"},{"adv":"0.1677","id":"lion","wr":"49.6603"},{"adv":"0.166","id":"earthshaker","wr":"46.4403"},{"adv":"0.1527","id":"earth-spirit","wr":"49.0158"},{"adv":"0.0915","id":"venomancer","wr":"43.9309"},{"adv":"0.0801","id":"slardar","wr":"46.9489"},{"adv":"0.056","id":"weaver","wr":"46.9922"},{"adv":"0.0095","id":"bloodseeker","wr":"45.2585"},{"adv":"-0.0112","id":"crystal-maiden","wr":"43.0446"},{"adv":"-0.0234","id":"dawnbreaker","wr":"42.6375"},{"adv":"-0.0613","id":"sniper","wr":"45.3046"},{"adv":"-0.0786","id":"sven","wr":"48.9707"},{"adv":"-0.1163","id":"snapfire","wr":"50.5259"},{"adv":"-0.1218","id":"phantom-lancer","wr":"46.6398"},{"adv":"-0.128","id":"mirana","wr":"44.8478"},{"adv":"-0.1474","id":"warlock","wr":"42.314"},{"adv":"-0.1712","id":"invoker","wr":"48.9475"},{"adv":"-0.1877","id":"storm-spirit","wr":"53.1177"},{"adv":"-0.2002","id":"grimstroke","wr":"49.2252"},{"adv":"-0.2068","id":"silencer","wr":"43.8847"},{"adv":"-0.2663","id":"magnus","wr":"49.3146"},{"adv":"-0.2715","id":"gyrocopter","wr":"47.3751"},{"adv":"-0.2979","id":"primal-beast","wr":"51.5903"},{"adv":"-0.3315","id":"ursa","wr":"45.5424"},{"adv":"-0.3446","id":"ogre-magi","wr":"44.9955"},{"adv":"-0.3674","id":"wraith-king","wr":"44.6598"},{"adv":"-0.3765","id":"tusk","wr":"49.0789"},{"adv":"-0.3952","id":"centaur-warrunner","wr":"44.0719"},{"adv":"-0.4082","id":"spirit-breaker","wr":"48.3818"},{"adv":"-0.4207","id":"vengeful-spirit","wr":"44.7462"},{"adv":"-0.4754","id":"doom","wr":"51.4482"},{"adv":"-0.4821","id":"bane","wr":"48.0959"},{"adv":"-0.4946","id":"marci","wr":"47.4258"},{"adv":"-0.5075","id":"treant-protector","wr":"45.5956"},{"adv":"-0.5492","id":"jakiro","wr":"44.3614"},{"adv":"-0.5572","id":"sand-king","wr":"46.5255"},{"adv":"-0.5825","id":"outworld-destroyer","wr":"45.4136"},{"adv":"-0.5966","id":"ancient-apparition","wr":"46.4211"},{"adv":"-0.6141","id":"lich","wr":"46.5801"},{"adv":"-0.6236","id":"dragon-knight","wr":"50.0015"},{"adv":"-0.6473","id":"necrophos","wr":"46.0124"},{"adv":"-0.6479","id":"alchemist","wr":"45.5702"},{"adv":"-0.6594","id":"axe","wr":"43.2323"},{"adv":"-0.66","id":"leshrac","wr":"50.8873"},{"adv":"-0.6617","id":"arc-warden","wr":"42.0812"},{"adv":"-0.6647","id":"juggernaut","wr":"42.0368"},{"adv":"-0.6706","id":"chen","wr":"44.734"},{"adv":"-0.6899","id":"rubick","wr":"51.1647"},{"adv":"-0.6982","id":"undying","wr":"45.0894"},{"adv":"-0.7518","id":"void-spirit","wr":"46.8323"},{"adv":"-0.7714","id":"bristleback","wr":"46.1959"},{"adv":"-0.7728","id":"beastmaster","wr":"46.9876"},{"adv":"-0.8185","id":"phoenix","wr":"48.9956"},{"adv":"-0.8382","id":"hoodwink","wr":"47.0266"},{"adv":"-0.9055","id":"broodmother","wr":"51.7768"},{"adv":"-0.9253","id":"lifestealer","wr":"47.2865"},{"adv":"-0.9697","id":"dark-willow","wr":"49.0507"},{"adv":"-0.9979","id":"dark-seer","wr":"47.6482"},{"adv":"-1.0071","id":"clockwerk","wr":"47.8907"},{"adv":"-1.0649","id":"shadow-demon","wr":"50.1782"},{"adv":"-1.0889","id":"dazzle","wr":"43.6474"},{"adv":"-1.0914","id":"pudge","wr":"46.5658"},{"adv":"-1.1291","id":"bounty-hunter","wr":"47.3257"},{"adv":"-1.14","id":"monkey-king","wr":"53.0552"},{"adv":"-1.1916","id":"zeus","wr":"44.3205"},{"adv":"-1.2009","id":"visage","wr":"41.2464"},{"adv":"-1.2478","id":"pangolier","wr":"51.2816"},{"adv":"-1.2939","id":"timbersaw","wr":"51.4753"},{"adv":"-1.3798","id":"tinker","wr":"49.5772"},{"adv":"-1.4498","id":"spectre","wr":"44.3601"},{"adv":"-1.6082","id":"keeper-of-the-light","wr":"49.3574"},{"adv":"-1.7073","id":"phantom-assassin","wr":"49.6046"},{"adv":"-1.7508","id":"winter-wyvern","wr":"46.3976"},{"adv":"-1.8636","id":"mars","wr":"51.5463"},{"adv":"-1.9226","id":"elder-titan","wr":"50.0445"},{"adv":"-2.1319","id":"razor","wr":"48.3831"},{"adv":"-2.2346","id":"windranger","wr":"48.017"},{"adv":"-3.0525","id":"brewmaster","wr":"47.6363"},{"adv":"-3.9837","id":"batrider","wr":"55.6068"}]}